StackIt/GUIapp.py
StackIt/__init__.py
StackIt/builder.py
StackIt/config.py
StackIt/decklist.py
StackIt/globals.py
StackIt/scraper.py
StackIt/watcher.py
StackIt/resources/HexLists/HexList-AllCards.dat
StackIt/resources/HexLists/HexList-Champion.dat
StackIt/resources/HexLists/HexList-Mercenary.dat
StackIt/resources/fonts/ufonts.com_humanist521bt-ultrabold-opentype.otf
StackIt/resources/hexicons/[ARDENT].png
StackIt/resources/hexicons/[ARMIESOFMYTH].png
StackIt/resources/hexicons/[ATK].png
StackIt/resources/hexicons/[BASIC].png
StackIt/resources/hexicons/[BLOOD].png
StackIt/resources/hexicons/[CANTATTACK].png
StackIt/resources/hexicons/[CANTBLOCK].png
StackIt/resources/hexicons/[CRUSH].png
StackIt/resources/hexicons/[DEFENSE].png
StackIt/resources/hexicons/[DEFENSIVE].png
StackIt/resources/hexicons/[DIAMOND].png
StackIt/resources/hexicons/[EXHAUST].png
StackIt/resources/hexicons/[FLIGHT].png
StackIt/resources/hexicons/[HEROFALL].png
StackIt/resources/hexicons/[INVINCIBLE].png
StackIt/resources/hexicons/[LETHAL].png
StackIt/resources/hexicons/[LIFEDRAIN].png
StackIt/resources/hexicons/[MUSTATTACK].png
StackIt/resources/hexicons/[ONESHOT].png
StackIt/resources/hexicons/[PRIMALDAWN].png
StackIt/resources/hexicons/[RAGE].png
StackIt/resources/hexicons/[RUBY].png
StackIt/resources/hexicons/[SAPPHIRE].png
StackIt/resources/hexicons/[SCARSOFWAR].png
StackIt/resources/hexicons/[SCATTEREDDESTINY].png
StackIt/resources/hexicons/[SHARDSOFFATE].png
StackIt/resources/hexicons/[SKYGUARD].png
StackIt/resources/hexicons/[SPEED].png
StackIt/resources/hexicons/[SPELLSHIELD].png
StackIt/resources/hexicons/[STEADFAST].png
StackIt/resources/hexicons/[SWIFTSTRIKE].png
StackIt/resources/hexicons/[UNDERWORLD].png
StackIt/resources/hexicons/[WILD].png
StackIt/resources/mana/Mana_0.png
StackIt/resources/mana/Mana_1.png
StackIt/resources/mana/Mana_10.png
StackIt/resources/mana/Mana_11.png
StackIt/resources/mana/Mana_12.png
StackItDecklist-1.4.0.dist-info/DESCRIPTION.rst
StackItDecklist-1.4.0.dist-info/METADATA
StackItDecklist-1.4.0.dist-info/RECORD
StackItDecklist-1.4.0.dist-info/WHEEL
StackItDecklist-1.4.0.dist-info/metadata.json
StackItDecklist-1.4.0.dist-info/top_level.txt
